nmdc/__init__.py
nmdc/test_data/__init__.py
nmdc-0.2.1.dist-info/LICENSE
nmdc-0.2.1.dist-info/METADATA
nmdc-0.2.1.dist-info/WHEEL
nmdc-0.2.1.dist-info/entry_points.txt
nmdc-0.2.1.dist-info/top_level.txt
nmdc-0.2.1.dist-info/RECORD
