Metadata-Version: 2.1
Name: nmdc
Version: 0.2.1
Summary: Command line toolbox of NMDC (https://microbiomedata.org/)
Home-page: https://microbiomedata.org/
Author: Bin Hu
Author-email: bhu@lanl.gov
License: BSD 3 "Clause"
Keywords: NMDC,microbiome,bioinformatics
Platform: UNKNOWN
Classifier: Development Status :: 2 - Pre-Alpha
Classifier: Intended Audience :: Science/Research
Classifier: Intended Audience :: Developers
Classifier: Operating System :: POSIX :: BSD
Classifier: Programming Language :: Python :: 3.6
Classifier: Programming Language :: Python :: 3.7
Classifier: Programming Language :: Python :: 3.8
Classifier: Programming Language :: Python :: 3 :: Only
Classifier: Topic :: Scientific/Engineering :: Bio-Informatics
Requires-Python: >=3.5.*
Requires-Dist: biolinkml (>=1.6.0)
Requires-Dist: pyyaml
Requires-Dist: requests
Requires-Dist: obonet
Requires-Dist: biopython
Requires-Dist: bcbio-gff (>=0.6.6)
Requires-Dist: click
